okd_camgi/__init__.py
okd_camgi/contexts.py
okd_camgi/interfaces.py
okd_camgi/main.py
okd_camgi/templates/index.html
okd_camgi-0.6.0.dist-info/LICENSE
okd_camgi-0.6.0.dist-info/METADATA
okd_camgi-0.6.0.dist-info/WHEEL
okd_camgi-0.6.0.dist-info/entry_points.txt
okd_camgi-0.6.0.dist-info/top_level.txt
okd_camgi-0.6.0.dist-info/RECORD
