Metadata-Version: 2.1
Name: okd-camgi
Version: 0.6.0
Summary: OKD Cluster Autoscaler Must Gather Investigator
Home-page: https://github.com/elmiko/okd-camgi
Author: michael mccune
Author-email: msm@opbstudios.com
License: GPLv3
Platform: UNKNOWN
License-File: LICENSE
Requires-Dist: bottle
Requires-Dist: cryptography (>=35.0.0)
Requires-Dist: jinja2
Requires-Dist: kubernetes
Requires-Dist: python-dateutil
Requires-Dist: pygments
Requires-Dist: pyyaml
